pylsd/__init__.py
pylsd/lsd.py
pylsd/bindings/__init__.py
pylsd/bindings/lsd_ctypes.py
pylsd/lib/darwin/liblsd.dylib
pylsd/lib/linux/liblsd.so
pylsd/lib/linux_arm/liblsd.so
pylsd/lib/win32/x64/lsd.dll
tezz_pylsd-1.1.dist-info/LICENSE
tezz_pylsd-1.1.dist-info/METADATA
tezz_pylsd-1.1.dist-info/WHEEL
tezz_pylsd-1.1.dist-info/top_level.txt
tezz_pylsd-1.1.dist-info/RECORD
