Metadata-Version: 2.1
Name: tezz-pylsd
Version: 1.1
Summary: tezz-pylsd is the python bindings for LSD - Line Segment Detector
Home-page: https://github.com/tezz-io/tezz-pylsd
Author: Tejas M R
Author-email: totejasmr@gmail.com
License: BSD
Keywords: LSD
License-File: LICENSE
